{
    "bakeTime": "",
    "calories": "235 kcal",
    "id": "R1185496",
    "ingredients": [
        "200 g winterpenen",
        "200 g kruimige aardappelen",
        "1  sjalot",
        "1 el traditionele olijfolie",
        "1  rundertartaar"
    ],
    "necessary": [],
    "nutrition": [
        "energie 235 kcal",
        "koolhydraten 21 g",
        "natrium 59 mg",
        "eiwit 13 g",
        "vet 10 g waarvan verzadigd 3 g",
        "vezels 4 g"
    ],
    "pageTitle": "Opperdepop: babyhutspot met tartaar 10-12 mnd recept",
    "portions": "2 porties",
    "prepTime": "20 min. bereiden",
    "preparation": [
        "Schil de wortels en snijd in plakjes. Schil de aardappelen en snijd in kleine blokjes. Kook de wortels en aardappelblokjes in een pan met een laag water afgedekt 15 min.",
        "Snipper de sjalot. Verhit de olie in een kleine koekenpan en fruit de sjalot op laag vuur. Laat niet bruin worden. Breek de tartaar in stukjes en bak met de ui rul en gaar.",
        "Giet de wortels en aardappelen af, maar vang het kookvocht op. Stamp de wortels en aardappelen tot een puree. Voeg eventueel wat kookvocht, opvolgmelk of moedermelk toe om de puree smeu\u00efger te maken. Meng de rulgebakken tartaar met sjalot door de puree."
    ],
    "spiciness": "",
    "tags": [
        "hollands",
        "stamppot",
        "kindergerecht",
        "winter",
        "in te vriezen"
    ],
    "tips": [
        "Bron: Opperdepop 2006, Albert Heijn",
        "Ingevroren kun je het hapje 2 maanden bewaren."
    ],
    "title": "Dit winterse hapje is z\u00f3 gemaakt wanneer je zelf ook hutspot eet.",
    "waitTime": ""
}