{
    "bakeTime": "1 uur 10 min. oventijd",
    "calories": "325 kcal",
    "id": "R1187068",
    "ingredients": [
        "1.2 kg bloemkool",
        "5 el traditionele olijfolie",
        "2 el Euroma Original spices by Jonnie Boer baharat kruidenmix",
        "1 schaal Tasty Tom trostomaat",
        "20 g verse platte peterselie",
        "100 g kappertjes",
        "100 g witte kaas"
    ],
    "necessary": [
        "bakpapier"
    ],
    "nutrition": [
        "energie 325 kcal",
        "koolhydraten 11 g",
        "natrium 740 mg",
        "eiwit 10 g",
        "vet 25 g waarvan verzadigd 6 g",
        "vezels 7 g"
    ],
    "pageTitle": "Geroosterde bloemkool met tomatensalsa recept",
    "portions": "4 personen",
    "prepTime": "10 min. bereiden",
    "preparation": [
        "Verwarm de oven voor op 180 \u00b0C. Verwijder de bladeren en steelaanzet van de bloemkool, zodat deze goed blijft liggen. Leg de bloemkool op een met bakpapier beklede bakplaat. Meng 2 el olie met de baharat en bestrijk de bloemkool ermee. Rooster de bloemkool in het midden van de oven in ca. 70 min. gaar of tot hij zacht is.",
        "Snijd ondertussen de tomaten in kwarten, verwijder de zaadlijsten en snijd het vruchtvlees in blokjes van \u00bd x \u00bd cm (brunoise). Snijd de peterselie fijn. Laat de kappertjes uitlekken en verkruimel de witte kaas. Meng de tomatenblokjes, peterselie en kappertjes met de rest van de olie tot een salsa. Breng op smaak met peper. Neem de bloemkool uit de oven, snijd in plakken en verdeel de tomatensalsa en witte kaas erover."
    ],
    "spiciness": "",
    "tags": [
        "glutenvrij",
        "vegetarisch",
        "oven",
        "hoofdgerecht",
        "wat eten we vandaag",
        "lente"
    ],
    "tips": [
        "De kern van een grote bloemkool blijft vrij stevig. Houd je van zachte bloemkool? Gebruik dan 2 kleine bloemkolen.",
        "Lekker met tortilla\u2019s en witvis, zoals kabeljauw. Het gerecht is dan niet meer vegetarisch en glutenvrij."
    ],
    "title": "De bloemkool gaat in zijn geheel in de oven en met de rest ben je slechts 10 minuten bezig. Easy!",
    "waitTime": ""
}