{
    "bakeTime": "",
    "calories": "260 kcal",
    "id": "R1185551",
    "ingredients": [
        "400 g mango-ananassticks",
        "400 ml vers sinaasappelsap",
        "300 g kokosyoghurt",
        "2 el gepelde pistachenoten"
    ],
    "necessary": [
        "blender of keukenmachine"
    ],
    "nutrition": [
        "energie 260 kcal",
        "koolhydraten 36 g",
        "natrium 30 mg",
        "eiwit 5 g",
        "vet 10 g waarvan verzadigd 5 g",
        "vezels 2 g"
    ],
    "pageTitle": "Mango-kokos-ananas-smoothie.  recept",
    "portions": "4 personen",
    "prepTime": "5 min. bereiden",
    "preparation": [
        "Doe de mango, ananas, het sinaasappelsap en de kokosyoghurt in de blender en mix 2 min. Hak ondertussen de pistachenoten grof. Schenk de smoothie in 4 glazen en verdeel de pistachenoten erover."
    ],
    "spiciness": "",
    "tags": [
        "vooraf te maken",
        "amerikaans",
        "engels",
        "brunch",
        "ontbijt",
        "tussendoortje",
        "pasen",
        "picknick",
        "vaderdag",
        "moederdag",
        "keukenmachine"
    ],
    "tips": [
        "In plaats van de blender kun je ook een keukenmachine gebruiken.",
        "Je kunt de smoothie 4 uur van tevoren maken. Bewaar afgedekt in de koelkast. Schud om of roer goed door voor het serveren."
    ],
    "title": "Topcombi van tropische smaken",
    "waitTime": ""
}