{
    "bakeTime": "",
    "calories": "",
    "id": "R1186408",
    "ingredients": [
        "2 cm verse gember",
        "1 l troebel appelsap",
        "2  kaneelstokjes",
        "1  steranijs",
        "5  kruidnagels"
    ],
    "necessary": [],
    "nutrition": [],
    "pageTitle": "Alcoholvrij gl\u00fchsap  recept",
    "portions": "5 personen",
    "prepTime": "5 min. bereiden",
    "preparation": [
        "Snijd de gember in plakjes. Verwarm de appelsap met de kaneelstokjes, steranijs, kruidnagels en gember 10 min. op laag vuur."
    ],
    "spiciness": "",
    "tags": [
        "drankje zonder alcohol",
        "kerst"
    ],
    "tips": [],
    "title": "Hier lopen kinderen warm voor \u00e9n ze worden er warm van: alcoholvrij gl\u00fcsap. ",
    "waitTime": ""
}