{
    "bakeTime": "",
    "calories": "725 kcal",
    "id": "R1189226",
    "ingredients": [
        "2  middelgrote eieren",
        "1  eetrijpe avocado",
        "\u00bd  courgette",
        "1  bosui",
        "1\u00bd el (olijf)olie",
        "\u00bd  citroen",
        "1 tl dijonmosterd",
        "400 g linzen in pot",
        "100 g verse spinazie",
        "125 g verse gerookte makreelfilet"
    ],
    "necessary": [],
    "nutrition": [
        "energie 725 kcal",
        "koolhydraten 34 g",
        "natrium 600 mg",
        "eiwit 33 g",
        "vet 48 g waarvan verzadigd 9 g",
        "vezels 11 g"
    ],
    "pageTitle": "Linzen-makreelsalade met avocado en ei recept",
    "portions": "2 personen",
    "prepTime": "20 min. bereiden",
    "preparation": [
        "Kook de eieren 7 min. Laat schrikken onder koud stromend water, pel ze en halveer. Snijd ondertussen de avocado overlangs doormidden. Verwijder de pit, schep het vruchtvlees met een lepel uit de schil en snijd in de breedte in plakjes. Snijd de courgette in plakjes van een \u00bd cm. Snijd de bosui in dunne ringetjes.",
        "Verhit de olie in een koekenpan en bak de courgette in 5 min. goudbruin. Pers de citroen uit.  Meng een \u00bd el citroensap met de mosterd en de rest van de olie en breng de dressing op smaak met peper.",
        "Spoel de linzen af en laat uitlekken. Doe de spinazie in een grote schaal. Verdeel hierover de linzen, courgetteplakjes, avocado, bosui en eieren. Verdeel de makreel in stukken erover en besprenkel met de dressing."
    ],
    "spiciness": "",
    "tags": [
        "glutenvrij",
        "lactosevrij",
        "gezond",
        "salade",
        "hoofdgerecht",
        "wat eten we vandaag",
        "suikerbewust"
    ],
    "tips": [
        "Dijonmosterd staat niet in de Schijf van Vijf en is een dagkeuze. Kijk voor meer uitleg over dag- en weekkeuzes op voedingscentrum.nl. "
    ],
    "title": "Makreel is ook heerlijk met linzen! In deze salade met veel groenten en ei. ",
    "waitTime": ""
}