{
    "bakeTime": "",
    "calories": "540 kcal",
    "id": "R1186674",
    "ingredients": [
        "150 g zilvervliesrijst",
        "2  uien",
        "2  tomaten",
        "3 cm verse gember",
        "1 el arachideolie",
        "2 el milde currypasta",
        "200 ml kokosmelk",
        "350 g kikkererwten in pot",
        "300 g verse zalmfilets",
        "400 g wilde spinazie"
    ],
    "necessary": [],
    "nutrition": [
        "energie 540 kcal",
        "koolhydraten 44 g",
        "natrium 250 mg",
        "eiwit 28 g",
        "vet 26 g waarvan verzadigd 12 g",
        "vezels 9 g"
    ],
    "pageTitle": "Indiase viscurry met kikkererwten en spinazie recept",
    "portions": "4 personen",
    "prepTime": "25 min. bereiden",
    "preparation": [
        "Kook de rijst in ruim water in 15 min. gaar. Giet af en laat met de deksel op de pan staan tot gebruik. Snijd ondertussen de uien in halve ringen en de tomaat in blokjes. Schil de gember en snijd fijn. ",
        "Verhit de olie in een wok en fruit de ui, gember en kruidenpasta 3 min. op laag vuur. Voeg de tomaat, kokosmelk en kikkererwten toe en breng al roerend aan de kook. Laat 5 min. op middelhoog vuur koken. Breng op smaak met peper en eventueel zout.",
        "Snijd ondertussen de zalm in blokjes van 2 x 2 cm. Snijd de spinazie grof. Voeg de zalm en spinazie toe aan de curry en schep voorzichtig om tot de spinazie is geslonken. Breng eventueel op smaak met zout. Serveer de curry met de rijst."
    ],
    "spiciness": "",
    "tags": [
        "glutenvrij",
        "lactosevrij",
        "zonder vlees",
        "indiaas",
        "aziatisch",
        "rijst",
        "hoofdgerecht",
        "koken"
    ],
    "tips": [
        "Lekker met een schijfje limoen."
    ],
    "title": "Houd je van romig \u00e9n van uitgesproken smaken? Ga dan voor deze heerlijk gekruide curry met zalm.",
    "waitTime": ""
}