{
    "bakeTime": "",
    "calories": "435 kcal",
    "id": "R1186072",
    "ingredients": [
        "250 g spaghetti",
        "400 g verse spinazie",
        "2 el tomatenpuree in blik",
        "275 g verse rundersoepballetjes",
        "1  kippenbouillontablet",
        "600 ml heet water",
        "250 g cherrytomaten"
    ],
    "necessary": [],
    "nutrition": [
        "energie 435 kcal",
        "koolhydraten 54 g",
        "natrium 970 mg",
        "eiwit 23 g",
        "vet 13 g waarvan verzadigd 5 g",
        "vezels 5 g"
    ],
    "pageTitle": "Spaghetti met spinazie, gehaktballetjes en tomaat recept",
    "portions": "4 personen",
    "prepTime": "10 min. bereiden",
    "preparation": [
        "Breek de spaghetti doormidden en doe samen met de spinazie, tomatenpuree, soepballetjes en hete bouillon in een ruime soeppan.",
        "Laat met de deksel op de pan op middelhoog vuur 10 min. koken. Schep regelmatig om en roer de spaghetti goed los.",
        "Halveer ondertussen de tomaten en voeg ze de laatste 5 min. toe. Breng op smaak met peper. Serveer direct."
    ],
    "spiciness": "",
    "tags": [
        "lactosevrij",
        "snel",
        "slank",
        "italiaans",
        "pasta",
        "hoofdgerecht",
        "camping",
        "wat eten we vandaag"
    ],
    "tips": [],
    "title": "Supersnel eenpansgerecht van Italiaanse bodem. ",
    "waitTime": ""
}