{
    "bakeTime": "",
    "calories": "245 kcal",
    "id": "R1185142",
    "ingredients": [
        "4  mini kipsat\u00e9spiesjes",
        "425 g minimaiskolfjes in blik",
        "175 ml kant-en-klare sat\u00e9saus",
        "50 g seroendeng"
    ],
    "necessary": [],
    "nutrition": [
        "energie 245 kcal",
        "koolhydraten 15 g",
        "natrium 595 mg",
        "eiwit 15 g",
        "vet 13 g waarvan verzadigd 6 g",
        "vezels 5 g"
    ],
    "pageTitle": "Kipsat\u00e9 met minimais recept",
    "portions": "4 personen",
    "prepTime": "15 min. bereiden",
    "preparation": [
        "Gril de kipsat\u00e9spiesjes op de plaat van het gourmetstel in 10 min. goudbruin en gaar. Keer regelmatig.  Laat de minimaiskolfjes uitlekken, leg ze de laatste 4 min. bij de kipsat\u00e9spiesjes en gril mee. Keer regelmatig.",
        "Verwarm ondertussen de sat\u00e9saus volgens de aanwijzingen op de verpakking.",
        "Serveer de kipsat\u00e9spiesjes met de minimaiskolfjes en sat\u00e9saus, bestrooi met de seroendeng."
    ],
    "spiciness": "",
    "tags": [
        "indonesisch",
        "aziatisch",
        "bijgerecht",
        "gourmet",
        "kerst",
        "herfst",
        "lente",
        "winter",
        "zomer",
        "grillen",
        "kerstbijgerechten"
    ],
    "tips": [],
    "title": "Minihapje: minispiesje en minimaiskolf.",
    "waitTime": ""
}