{
    "bakeTime": "",
    "calories": "90 kcal",
    "id": "R1187171",
    "ingredients": [
        "5  limoenen",
        "\u00bd teen knoflook",
        "\u00bd el verse gember",
        "1  rode peper",
        "300 g verse kabeljauwfilets",
        "1 el mais in blik",
        "1 el verse granaatappelpitjes",
        "8 takjes verse koriander",
        "1  kleine rode ui"
    ],
    "necessary": [],
    "nutrition": [
        "energie 90 kcal",
        "koolhydraten 6 g",
        "natrium 55 mg",
        "eiwit 14 g",
        "vet 1 g waarvan verzadigd 0 g",
        "vezels 2 g"
    ],
    "pageTitle": "Bart van Olphens kabeljauw ceviche recept",
    "portions": "4 personen",
    "prepTime": "25 min. bereiden",
    "preparation": [
        "Rasp de schil van 1/2 limoen en houdt dit apart. Pers alle limoenen uit en giet het sap in een kom. Voeg de knoflook, gember en de helft van de rode peper toe. ",
        "Snijd de kabeljauw met een scherp koksmes in de lengte doormidden en vervolgens in plakken van 1 centimeter dik. Verdeel de plakken kabeljauw over de borden. Schenk het limoensap over de kabeljauw en laat 10-12 min. staan. ",
        "Meng ondertussen de ma\u00efs met de granaatappelpitten en de koriander.",
        "Snijd de rode ui in dunne ringen en leg ze 5 minuten in water met ijsblokjes.",
        "Verdeel de ma\u00efs, granaatappelpitten, de koriander en de ui over de ceviche. Bestrooi met limoenrasp en de rest van de rode peper. "
    ],
    "spiciness": "pittig",
    "tags": [
        "slank",
        "zuid amerikaans",
        "lunch",
        "voorgerecht",
        "borrel"
    ],
    "tips": [
        "Bron: Het viskookboek, Bart van Olphen."
    ],
    "title": "Het geheim van een goede ceviche: de citrusmarinade. ",
    "waitTime": ""
}