{
    "bakeTime": "",
    "calories": "40 kcal",
    "id": "R1185584",
    "ingredients": [
        "400 g verse aardbeien",
        "1  limoen",
        "15 g verse basilicum",
        "2 el poedersuiker"
    ],
    "necessary": [],
    "nutrition": [
        "energie 40 kcal",
        "koolhydraten 9 g",
        "natrium 3 mg",
        "eiwit 1 g",
        "vezels 1 g"
    ],
    "pageTitle": "Gemarineerde aardbeien met limoen en basilicum.  recept",
    "portions": "4 personen",
    "prepTime": "10 min. bereiden",
    "preparation": [
        "Verwijder de kroontjes van de aardbeien en halveer ze. Rasp de groene schil van de limoen en pers de helft van de vrucht uit.  Pluk de blaadjes van de takjes basilicum en snijd in dunne reepjes.",
        "Meng de aardbeien, het limoenrasp en -sap, de poedersuiker en het basilicum en laat 10 min. marineren."
    ],
    "spiciness": "",
    "tags": [
        "glutenvrij",
        "lactosevrij",
        "brunch",
        "nagerecht",
        "pasen",
        "lente",
        "zomer",
        "slank"
    ],
    "tips": [
        "Lekker met lobbig geslagen slagroom (het gerecht is dan niet meer lactosevrij)."
    ],
    "title": "Sluit je etentje af met dit supertrio! ",
    "waitTime": "10 min. wachten"
}