{
    "bakeTime": "",
    "calories": "115 kcal",
    "id": "R1186066",
    "ingredients": [
        "1  citroen",
        "1 teen knoflook",
        "10 g verse platte peterselie",
        "50 ml extra vergine olijfolie"
    ],
    "necessary": [],
    "nutrition": [
        "energie 115 kcal",
        "natrium 1 mg",
        "vet 13 g waarvan verzadigd 2 g"
    ],
    "pageTitle": "Gremolata recept",
    "portions": "4 personen",
    "prepTime": "5 min. bereiden",
    "preparation": [
        "Rasp de gele schil van de citroen. Snijd de knoflook fijn en de blaadjes peterselie.  Meng het citroenrasp met de knoflook, peterselie en olijfolie. Breng op smaak met peper en eventueel zout. "
    ],
    "spiciness": "",
    "tags": [
        "glutenvrij",
        "lactosevrij",
        "vooraf te maken",
        "italiaans",
        "bijgerecht",
        "barbecue"
    ],
    "tips": [
        "Je kunt de gremolata 1 dag van tevoren bereiden. Bewaar afgedekt in de koelkast.",
        "Lekker over Italiaans stoofvlees, gegrilde kip of vis of de pastasalade met wortel, feta & sinaasappel."
    ],
    "title": "Mengsel van citroenrasp, knoflook en peterselie dat veel gebruikt wordt in de Italiaanse keuken.",
    "waitTime": ""
}