{
    "bakeTime": "",
    "calories": "365 kcal",
    "id": "R1195056",
    "ingredients": [
        "8 sneetjes volkorenbrood",
        "125 g 100% pindakaas met stukjes pinda's",
        "300 g rauwkost komkommer"
    ],
    "necessary": [],
    "nutrition": [
        "energie 365 kcal",
        "koolhydraten 31 g waarvan suikers 4 g",
        "natrium 320 mg",
        "eiwit 16 g",
        "vet 18 g waarvan verzadigd 3 g",
        "vezels 8 g"
    ],
    "pageTitle": "Volkorenbrood met pindakaas en rauwkost recept",
    "portions": "4 personen",
    "prepTime": "5 min. bereiden",
    "preparation": [
        "Besmeer de sneetjes brood met de pindakaas.",
        "Verdeel de rauwkost komkommer over de helft van de sneetjes brood. Dek af met de rest van de sneetjes met de besmeerde kant naar beneden en snijd doormidden."
    ],
    "spiciness": "",
    "tags": [
        "vegetarisch",
        "gezond",
        "budget",
        "brood/sandwiches",
        "lunch"
    ],
    "tips": [],
    "title": "Volkorenbrood met pindakaas en rauwkost komkommer is de 2.0 versie van het oude vertrouwde bammetje pindakaas!",
    "waitTime": ""
}