{
    "bakeTime": "",
    "calories": "355 kcal",
    "id": "R1197076",
    "ingredients": [
        "2  sinaasappels",
        "2  Conference peren",
        "10 g verse gemberwortel",
        "40 g ongebrande amandelen",
        "800 g magere kwark",
        "120 g Geroosterde muesli zaden"
    ],
    "necessary": [
        "hoge glazen"
    ],
    "nutrition": [
        "energie 355 kcal",
        "koolhydraten 38 g waarvan suikers 21 g",
        "natrium 80 mg",
        "eiwit 24 g",
        "vet 10 g waarvan verzadigd 1 g",
        "vezels 8 g"
    ],
    "pageTitle": "Kwark met peer, sinaasappel en muesli recept",
    "portions": "4 personen",
    "prepTime": "10 min. bereiden",
    "preparation": [
        " Boen de sinaasappels schoon en rasp de oranje schil. Snijd het witte vlies van de sinaasappels en snijd de partjes tussen de vliesjes uit, vang het sap op in een kom. ",
        " Schil de peren, snijd in de lengte in kwarten en verwijder het klokhuis. Snijd het vruchtvlees in blokjes van ca. 1 cm en meng met het sinaasappelsap. Schil en rasp de gember erover en meng erdoor.",
        " Hak de amandelen grof. Verdeel achtereenvolgens de helft van de kwark, de helft van de muesli en de helft van het fruitmengsel over de glazen. Herhaal dit en garneer met de amandelen en het sinaasappelrasp."
    ],
    "spiciness": "",
    "tags": [
        "gezond",
        "ontbijt"
    ],
    "tips": [
        "Gember over? Zet er verse gemberthee van."
    ],
    "title": "Een fris, zoet en knapperig begin van de dag. Begin je dag gezond en lekekr met deze kwark met peer, sinaasappel en muesli.",
    "waitTime": ""
}