{
    "bakeTime": "",
    "calories": "125 kcal",
    "id": "R1190901",
    "ingredients": [
        "400 g zoete aardappelen",
        "\u00bd  rode peper",
        "150 g kikkererwten in blik",
        "1 tl garam masala"
    ],
    "necessary": [
        "staafmixer met hoge beker"
    ],
    "nutrition": [
        "energie 125 kcal",
        "koolhydraten 24 g",
        "natrium 80 mg",
        "eiwit 3 g",
        "vet 1 g waarvan verzadigd 0 g",
        "vezels 5 g"
    ],
    "pageTitle": "Pittige zoete-aardappelspread recept",
    "portions": "4 personen",
    "prepTime": "15 min. bereiden",
    "preparation": [
        "Schil de zoete aardappel, snijd in blokjes van 2 cm en kook in een laagje water in 8 min. gaar. Giet af, laat iets a\u009afkoelen en doe ze in een hoge beker.",
        "Halveer de rode peper in de lengte en verwijder met een scherp mesje de zaadlijsten. Snijd het vruchtvlees in stukjes en doe ook in de beker. Laat de kikkererwten uitlekken en voeg de inhoud toe, samen met de garam masala. Pureer tot een spread en breng eventueel op smaak met zout."
    ],
    "spiciness": "",
    "tags": [
        "vegetarisch",
        "lactosevrij",
        "glutenvrij",
        "slank",
        "tussendoortje",
        "borrelhapje",
        "bijgerecht",
        "picknick",
        "borrel"
    ],
    "tips": [
        "Je kunt de spread 3 dagen van tevoren bereiden. Bewaar in een afgesloten bakje in de koelkast."
    ],
    "title": "Wat een goed idee: groenten op brood. Zo haal je die 250 gram per dag makkelijk! ",
    "waitTime": ""
}