{
    "bakeTime": "",
    "calories": "230 kcal",
    "id": "R1193469",
    "ingredients": [
        "2 el milde olijfolie",
        "800 g verse spinazie",
        "4  middelgrote eieren",
        "200 g h\u00fcttenk\u00e4se"
    ],
    "necessary": [
        "staafmixer"
    ],
    "nutrition": [
        "energie 230 kcal",
        "koolhydraten 3 g waarvan suikers 1 g",
        "natrium 240 mg",
        "eiwit 19 g",
        "vet 15 g waarvan verzadigd 4 g",
        "vezels 4 g"
    ],
    "pageTitle": "Mealprep met spinazie, h\u00fcttenk\u00e4se en gekookt eitje recept",
    "portions": "4 porties",
    "prepTime": "15 min. bereiden",
    "preparation": [
        "Verhit \u00bc van de olijfolie in een grote wok of diepe hapjespan op middelhoog vuur. Laat hierin een kwart van de spinazie al omscheppend slinken. Schep in een vergiet en laat uitlekken. Herhaal tot de spinazie op is.",
        "Kook de eieren in 6 min. halfzacht. Pureer de h\u00fcttenk\u00e4se met een staafmixer glad en breng op smaak met versgemalen peper en zout. Doe de spinazie in een schaal. Schep de h\u00fcttenk\u00e4se door de spinazie. Serveer met de eieren."
    ],
    "spiciness": "",
    "tags": [
        "zonder vlees/vis",
        "glutenvrij",
        "vooraf te maken",
        "bijgerecht",
        "bakken",
        "mealprep"
    ],
    "tips": [
        "Bewaar de eieren ongepeld in de koelkast. ",
        "Maak je de spinazie voor meerdere dagen? Laat zo snel mogelijk afkoelen en bewaar los van de h\u00fcttenk\u00e4se. Bewaar de spinazie in een aparte, goed afgesloten bakken in de koelkast. Bewaar maximaal 2 dagen. Je kunt de afgekoelde spinazie ook goed invriezen. In een goed afgesloten bak in de vriezer is de spinazie max. 3 maanden bewaren. "
    ],
    "title": "Deze snelle spinazie is helemaal homemade.",
    "waitTime": ""
}