{
    "bakeTime": "",
    "calories": "290 kcal",
    "id": "R1194384",
    "ingredients": [
        "8 sneetjes volkorenbrood",
        "8  radijsjes",
        "150 g Milner Slankie smeerkaas 20+",
        "200 g gerookte forelfilet",
        "2 takjes verse platte peterselie"
    ],
    "necessary": [
        "broodrooster"
    ],
    "nutrition": [
        "energie 290 kcal",
        "koolhydraten 28 g waarvan suikers 2 g",
        "natrium 1040 mg",
        "eiwit 28 g",
        "vet 6 g waarvan verzadigd 3 g",
        "vezels 5 g"
    ],
    "pageTitle": "Toast met smeerkaas & gerookte forel recept",
    "portions": "4 personen",
    "prepTime": "10 min. bereiden",
    "preparation": [
        "Rooster de sneetjes brood in de broodrooster.",
        "Snijd de radijsjes in plakjes. Besmeer de sneetjes brood met de smeerkaas en beleg met de forelfilet en radijs. Garneer met wat blaadjes peterselie en bestrooi met peper."
    ],
    "spiciness": "",
    "tags": [
        "gezond",
        "slank",
        "budget",
        "brood/sandwiches",
        "lunch",
        "brunch"
    ],
    "tips": [
        "Vervang de forelfilet door avocado.",
        "Lekker met plakjes gekookt ei."
    ],
    "title": "Wie houdt er niet van smeerkaas? Gerookte forel en radijsjes erbij en je toast is klaar.",
    "waitTime": ""
}