{
    "bakeTime": "",
    "calories": "60 kcal",
    "id": "R1191582",
    "ingredients": [
        "1 el Leentjes poederpret",
        "1  Perla espresso forte capsule",
        "150 ml magere melk"
    ],
    "necessary": [
        "viltstift",
        "stevig papier",
        "theezeefje"
    ],
    "nutrition": [
        "energie 60 kcal",
        "koolhydraten 10 g",
        "natrium 80 mg",
        "eiwit 5 g"
    ],
    "pageTitle": "Cappuccino met kerstboom recept",
    "portions": "1 portie",
    "prepTime": "5 min. bereiden",
    "preparation": [
        "Vouw het papier dubbel. Teken er op de vouw met een stift een half kerstboompje van ca. 5-6 cm hoog op. Knip uit. Leg het theezeefje in een klein schaaltje. Doe van elke kleur poedersuiker een klein beetje in het zeefje.",
        "Maak de espresso in een cappuccinokopje. Schuim de melk op in een melkschuimer. Schep het melkschuim op de espresso. Strijk glad. Leg het sjabloontje of het uitgeknipte kerstboompje op de koffie en bestrooi met behulp van het zeefje met de 4 kleuren poedersuiker. "
    ],
    "spiciness": "",
    "tags": [
        "glutenvrij",
        "drankje zonder alcohol",
        "kerst"
    ],
    "tips": [],
    "title": "Het feest begint al bij de koffie. Want ook van de koffie maken we een kerstfeestje.",
    "waitTime": ""
}