{
    "bakeTime": "",
    "calories": "430 kcal",
    "id": "R1193157",
    "ingredients": [
        "4 sneetjes wit vloerbrood",
        "4 plakken Goudse jong belegen",
        "2 plakken roasted ham",
        "15 g ongezouten roomboter in de kuip"
    ],
    "necessary": [
        "airfryer"
    ],
    "nutrition": [
        "energie 430 kcal",
        "koolhydraten 35 g waarvan suikers 1 g",
        "natrium 800 mg",
        "eiwit 22 g",
        "vet 22 g waarvan verzadigd 14 g",
        "vezels 1 g"
    ],
    "pageTitle": "Tosti airfryer recept",
    "portions": "2 personen",
    "prepTime": "10 min. bereiden",
    "preparation": [
        "Verwarm de airfryer voor op 180 \u00b0C. Beleg een sneetje brood achtereenvolgens met een plak kaas, plak ham en nog een plak kaas. Dek af met een sneetje brood. Maak zo nog een tosti.",
        "Besmeer de buitenkant van de tosti met de helft van de boter. Bak 1 tosti in 5 min. goudbruin in de airfryer. Keer halverwege. Bak zo nog een tosti."
    ],
    "spiciness": "",
    "tags": [
        "brood/sandwiches",
        "lunch",
        "bakken",
        "airfryer"
    ],
    "tips": [
        "Lekker met ketchup"
    ],
    "title": "Wist je dat je tosti ook perfect krokant uit de airfryer komt? Nu wel.",
    "waitTime": "10 min. wachten"
}