{
    "bakeTime": "",
    "calories": "95 kcal",
    "id": "R1195800",
    "ingredients": [
        "40 ml wodka",
        "280 ml bruisend mineraalwater"
    ],
    "necessary": [],
    "nutrition": [
        "energie 95 kcal"
    ],
    "pageTitle": "Hard seltzer basisrecept recept",
    "portions": "1 persoon",
    "prepTime": "10 min. bereiden",
    "preparation": [
        "Meng de wodka en het mineraalwater. Serveer eventueel met ijsblokjes.\u00a0"
    ],
    "spiciness": "",
    "tags": [
        "glutenvrij",
        "lactosevrij",
        "drankje met alcohol",
        "borrel"
    ],
    "tips": [
        "Een seltzer is een Amerikaans drankje dat oorspronkelijk gefermenteerd is, met dank aan gist. Omdat dit thuis lastig na te maken is zonder ingewikkelde apparatuur, hebben we voor de eenvoudige versie gekozen van mineraalwater en wodka. Aan deze basis kun je alle smaken toevoegen die je maar wilt. Die smaken kun je toevoegen door een \u2018smaak\u2019 wodka te kiezen, maar ook door die wodka zelf te \u2018infuseren\u2019. "
    ],
    "title": "Een seltzer is een Amerikaans drankje dat oorspronkelijk gefermenteerd is. In dit basisrecept kiezen we voor de eenvoudige versie van mineraalwater en wodka. ",
    "waitTime": ""
}