{
    "bakeTime": "25 min. oventijd",
    "calories": "650 kcal",
    "id": "R1192970",
    "ingredients": [
        "600 g koelvers pizzadeeg met tomatensaus",
        "250 g Bellezza mozzarella",
        "50 g goudsalami",
        "250 g diepvries gegrilde groenten",
        "450 g diepvries spruitjes",
        "45 g koelverse pestospread"
    ],
    "necessary": [
        "bakpapier"
    ],
    "nutrition": [
        "energie 650 kcal",
        "koolhydraten 53 g waarvan suikers 10 g",
        "natrium 920 mg",
        "eiwit 28 g",
        "vet 32 g waarvan verzadigd 11 g",
        "vezels 10 g"
    ],
    "pageTitle": "Plaatpizza met spruitjes en salami recept",
    "portions": "4 personen",
    "prepTime": "10 min. bereiden",
    "preparation": [
        "Verwarm de oven voor op 180 \u00b0C. Rol het deeg uit de pizzakit op een met bakpapier beklede bakplaat en duw of rol het deeg wat verder uit, zodat het grootste deel van de bakplaat ermee bedekt is. Verdeel de tomatensaus uit de pizzakit erover.",
        "Snijd de mozzarella in plakjes en verdeel over het deeg. Verdeel de salami erover.",
        "Laat de gegrilde groenten uitlekken in een zeef. Halveer de spruiten. Verdeel de gegrilde groenten en spruiten over de pizza. Bak de pizza ca. 25 min. in het midden van de oven. Neem uit de oven en verdeel vlak voor serveren de pestospread erover."
    ],
    "spiciness": "",
    "tags": [
        "budget",
        "oven",
        "hoofdgerecht",
        "wat eten we vandaag"
    ],
    "tips": [],
    "title": "Pizza met spruitjes? Yes, bak ze mee voor een lekkere 'bite'.",
    "waitTime": ""
}