{
    "bakeTime": "",
    "calories": "435 kcal",
    "id": "R1197067",
    "ingredients": [
        "4 el milde olijfolie",
        "1 teen knoflook",
        "15 g verse basilicum",
        "2  tomaten",
        "250 g mozzarella",
        "8 sneetjes volkorenbrood"
    ],
    "necessary": [
        "staafmixer met hoge beker"
    ],
    "nutrition": [
        "energie 435 kcal",
        "koolhydraten 29 g waarvan suikers 3 g",
        "natrium 440 mg",
        "eiwit 19 g",
        "vet 26 g waarvan verzadigd 11 g",
        "vezels 5 g"
    ],
    "pageTitle": "Tosti met tomaat en mozzarella recept",
    "portions": "4 personen",
    "prepTime": "15 min. bereiden",
    "preparation": [
        "Doe de helft van de olie met de knoflook en basilicumblaadjes in een hoge beker en pureer met de staafmixer tot een olie. Snijd de tomaat en mozzarella in dunne plakken.",
        " Bestrijk de helft van de sneetjes brood met de basilicumolie. Beleg met de tomaat en mozzarella en breng op smaak met peper en eventueel zout. Bedek met de rest van de sneetjes brood.",
        " Verhit 2 grote koekenpannen met de rest van de olie en bak de tosti\u2019s in ca. 6 min. op middelhoog vuur. Keer halverwege. Snijd schuin doormidden en serveer."
    ],
    "spiciness": "",
    "tags": [
        "gezond",
        "zonder vlees/vis",
        "brood/sandwiches",
        "lunch",
        "camping",
        "bakken"
    ],
    "tips": [],
    "title": "Van deze lunchklassieker krijg je nooit genoeg. Een tosti met tomaat en mozzarella is altijd een goed idee.",
    "waitTime": ""
}