{
    "bakeTime": "",
    "calories": "295 kcal",
    "id": "R1197073",
    "ingredients": [
        "8 sneetjes volkorenbrood",
        "2 tl amandelschaafsel",
        "2  Conference peren",
        "400 g cottagecheese"
    ],
    "necessary": [
        "broodrooster"
    ],
    "nutrition": [
        "energie 295 kcal",
        "koolhydraten 37 g waarvan suikers 10 g",
        "natrium 520 mg",
        "eiwit 20 g",
        "vet 6 g waarvan verzadigd 3 g",
        "vezels 6 g"
    ],
    "pageTitle": "Toast met cottagecheese en peer recept",
    "portions": "4 personen",
    "prepTime": "10 min. bereiden",
    "preparation": [
        " Rooster de sneetjes brood in de broodrooster. Verhit ondertussen een koekenpan zonder olie of boter en rooster het amandelschaafsel in ca. 3 min. op middelhoog vuur goudbruin. Laat afkoelen op een bord.",
        "Snijd de peren in de lengte in kwarten, verwijder het klokhuis en snijd het vruchtvlees in de lengte in plakken.",
        "Besmeer de sneetjes brood met de cottagecheese en verdeel de peer erover. Bestrooi met het amandelschaafsel en breng op smaak met versgemalen peper."
    ],
    "spiciness": "",
    "tags": [
        "gezond",
        "slank",
        "brood/sandwiches",
        "ontbijt"
    ],
    "tips": [],
    "title": "Een gezond ontbijt is een goed begin van iedere dag. Deze toast met cottagecheese is eenvoudig, maar wel een origineel begin van je dag.",
    "waitTime": ""
}