{
    "bakeTime": "1 uur oventijd",
    "calories": "605 kcal",
    "id": "R1191269",
    "ingredients": [
        "200 g gorgonzola piccante 48+",
        "450 g ricotta",
        "125 g cr\u00e8me fra\u00eeche",
        "3  sjalotjes",
        "2 tenen knoflook",
        "4 takjes verse tijm",
        "2 el milde olijfolie",
        "900 g diepvries tuinerwten",
        "115 g ongezouten pecannoten",
        "700 g pompoen lasagnebladen"
    ],
    "necessary": [
        "handmixer",
        "rechthoekige ovenschaal (20 x 30 cm)"
    ],
    "nutrition": [
        "energie 605 kcal",
        "koolhydraten 26 g",
        "natrium 480 mg",
        "eiwit 22 g",
        "vet 44 g waarvan verzadigd 19 g",
        "vezels 9 g"
    ],
    "pageTitle": "Pompoenlasagne met pecannoten & gorgonzolasaus recept",
    "portions": "6 personen",
    "prepTime": "25 min. bereiden",
    "preparation": [
        "Verwarm de oven voor op 180 \u00b0C. Snijd de gorgonzola in stukjes. Meng de ricotta met de handmixer met de gorgonzola en cr\u00e8me fra\u00eeche tot een zo glad mogelijk mengsel. Snipper de sjalotjes en snijd de knoflook fijn. Ris de blaadjes tijm van de takjes. ",
        "Verhit de helft van de olijfolie in een koekenpan en fruit de sjalot, knoflook en ui 3 min. op laag vuur. Doe de ontdooide tuinerwten in een vergiet en giet er kokend water over. Laat goed uitlekken en meng met de sjalot, knoflook en tijm. Pureer met de staafmixer en breng op smaak met peper en eventueel zout. Hak de noten fijn.",
        "Vet de ovenschaal in met de rest van de olie. Maak laagjes van telkens \u00bc van de pompoenlasagne, \u2153 van de tuinerwten en \u2153 ricotta. Bestrooi met de noten. Laat in ca. 60 min gaar worden in de oven. Dek indien nodig af met aluminiumfolie als de noten te donker worden."
    ],
    "spiciness": "",
    "tags": [
        "zonder vlees/vis",
        "oven",
        "hoofdgerecht",
        "herfst"
    ],
    "tips": [],
    "title": "De lasagnebladen zijn gemaakt van pompoen. Dat betekent niet alleen minder koolhydraten, maar ook meer smaak.",
    "waitTime": ""
}