{
    "bakeTime": "30 min. oventijd",
    "calories": "380 kcal",
    "id": "R1197451",
    "ingredients": [
        "\u00bd  knolselderij",
        "600 g winterpeen",
        "1  prei",
        "3 el milde olijfolie",
        "300 g kipfilets",
        "1 el Euroma Original spices Jonny Boer Al-Andalus",
        "100 g geraspte oude kaas 48+"
    ],
    "necessary": [
        "bakpapier"
    ],
    "nutrition": [
        "energie 380 kcal",
        "koolhydraten 15 g waarvan suikers 7 g",
        "natrium 440 mg",
        "eiwit 28 g",
        "vet 21 g waarvan verzadigd 8 g",
        "vezels 11 g"
    ],
    "pageTitle": "Traybake kip, knolselderij, winterpeen en oude kaas recept",
    "portions": "4 personen",
    "prepTime": "10 min. bereiden",
    "preparation": [
        "Verwarm de oven voor op 200 \u00b0C. Schil de halve knolselderij en snijd in blokjes van ca. 1\u00bd  cm. Schil de winterpenen en snijd in schuine plakken van ca. 1 cm. Halveer de prei, spoel onder koud stromend water en snijd in halve ringen van ca. 1 cm.",
        "Verdeel de groenten over een met bakpapier beklede bakplaat, besprenkel met \u2154  van de olie en breng op smaak met peper en eventueel zout. Bak ca. 30 min in het midden van de oven.",
        "Snijd ondertussen de kipfilets in de lengte doormidden. Maak een marinade van de rest van de olie en de specerijenmelange en marineer de kip erin.",
        "Leg na 20 min. baktijd de kip op de groenten, verdeel de kaas erover en bak de laatste ca. 10 min. mee tot de kip gaar, maar nog sappig is."
    ],
    "spiciness": "",
    "tags": [
        "glutenvrij",
        "budget",
        "oven",
        "hoofdgerecht",
        "wat eten we vandaag",
        "herfst"
    ],
    "tips": [
        "Vervang de kip door 300 g vegetarische kipstukjes en de geraspte oude kaas door ovengratin geraspte kaas."
    ],
    "title": "Van vergeten groente naar gegeten groente: dat is knolselderij. Een groente met een heerlijke smaak, perfect voor in ovengerechten, zoals in deze traybake met kip en oude kaas. ",
    "waitTime": ""
}