{
    "bakeTime": "",
    "calories": "545 kcal",
    "id": "R810618",
    "ingredients": [
        "75 g boter",
        "1  sjalot",
        "2 sneetjes witbrood",
        "50 ml halfvolle melk",
        "1 bakje Hollandse garnalen",
        "400 g gehakt",
        "1  ei",
        "1 mespunt nootmuskaat",
        "50 g bloem"
    ],
    "necessary": [],
    "nutrition": [
        "energie 545 kcal",
        "koolhydraten 18 g",
        "eiwit 27 g",
        "vet 40 g"
    ],
    "pageTitle": "Jordanese gehaktballen recept",
    "portions": "4 personen",
    "prepTime": "40 min. bereiden",
    "preparation": [
        "Verhit 25 g boter in een koekenpan en fruit de sjalot 3 min. Neem uit de pan. Week ondertussen het brood in de melk. Knijp uit en meng in een kom met de sjalot, garnalen, het gehakt en ei. Voeg de nootmuskaat, peper en royaal zout toe.",
        "Vorm met natte handen 8 ballen van het gehakt en rol ze door de bloem. Verhit 50 g boter in dezelfde koekenpan en braad de gehaktballen op hoog vuur rondom aan. Zet het vuur laag en bak in 15 min. gaar. Draai regelmatig."
    ],
    "spiciness": "",
    "tags": [
        "hollands",
        "bijgerecht",
        "bakken"
    ],
    "tips": [],
    "title": "",
    "waitTime": ""
}