{
    "bakeTime": "2 uur 30 min. oventijd",
    "calories": "300 kcal",
    "id": "R824350",
    "ingredients": [
        "6  middelgrote eieren",
        "350 g fijne kristalsuiker",
        "1 mespunt zout",
        "1 el maizena",
        "3 el bietensap",
        "1  citroen",
        "500 g verse aardbeien",
        "350 g fijne kristalsuiker",
        "250 ml verse slagroom"
    ],
    "necessary": [
        "bakpapier"
    ],
    "nutrition": [
        "energie 300 kcal",
        "koolhydraten 43 g",
        "natrium 55 mg",
        "eiwit 5 g",
        "vet 12 g waarvan verzadigd 6 g",
        "vezels 1 g"
    ],
    "pageTitle": "Pink pavlova, roze meringue. recept",
    "portions": "10 porties",
    "prepTime": "30 min. bereiden",
    "preparation": [
        "Verwarm de oven voor op 150 \u00b0C. Splits de eieren. Klop de eiwitten met suiker en zout stijf tot het glanst. Klop de maizena en het bietensap erdoor.",
        "Schep het eiwit in een cirkel van 22 cm doorsnede op een met bakpapier beklede bakplaat. Bak in het midden van de oven op 140 \u00b0C in ca. 2 uur gaar. Zet de oven uit en laat nog ca. 30 min. in de oven staan. Neem eruit en laat in 1 uur afkoelen.",
        "Rasp ondertussen de gele schil van een schoongeboende citroen en pers de vrucht uit. Snijd de kroontjes van de aardbeien en halveer de aardbeien. Schep ze om met het sap, rasp en suiker. Laat 1 uur marineren.",
        "Klop de slagroom stijf en schep op de afgekoelde pavlova. Verdeel de aardbeien erover en serveer direct. Bon app\u00e9tit!"
    ],
    "spiciness": "",
    "tags": [
        "oven",
        "gebak",
        "nagerecht",
        "moederdag",
        "zomer"
    ],
    "tips": [],
    "title": "De pavlova krijgt zijn mooie, roze kleur door het bietensap.",
    "waitTime": "2 uur wachten"
}