{
    "bakeTime": "",
    "calories": "270 kcal",
    "id": "R830928",
    "ingredients": [
        "3 cm verse gember",
        "2 el Japanse sojasaus",
        "2 el olijfolie",
        "2 tl sesamolie",
        "1 el donkerbruine basterdsuiker",
        "2 tenen knoflook",
        "1 schaal varkensfiletlapjes \u00e0 la minute",
        "2  komkommers",
        "6 el zoete chilisaus"
    ],
    "necessary": [],
    "nutrition": [
        "energie 270 kcal",
        "koolhydraten 18 g",
        "eiwit 19 g",
        "vet 13 g waarvan verzadigd 0 g"
    ],
    "pageTitle": "Oosterse filetlapjes en komkommer recept",
    "portions": "4 personen",
    "prepTime": "20 min. bereiden",
    "preparation": [
        "Steek de barbecue aan. Rasp de gember fijn. Meng in een kom de gember, sojasaus, olijfolie, sesamolie, basterdsuiker en knoflook tot een marinade. Laat de varkensfiletlapjes hierin minimaal 30 min. marineren.",
        "Snijd de komkommers in de lengte in vieren. Verwijder de zaadlijsten met een theelepel en snijd het vruchtvlees in piepkleine blokjes. Meng met de chilisaus.",
        "Gril de filetlapjes op de barbecue in 4 min. bruin en gaar. Keer halverwege. Schep de komkommer over de filetlapjes en serveer. Lekker met mie of noedels."
    ],
    "spiciness": "",
    "tags": [
        "aziatisch",
        "hoofdgerecht",
        "zomer",
        "grillen"
    ],
    "tips": [],
    "title": "",
    "waitTime": "30 min. wachten"
}